README.md
naipyext/__init__.py
naipyext/autotime.py
naipyext/be.py
naipyext/be_o.py
naipyext/ns.py
naipyext/pt.py
naipyext/sp.py
naipyext-0.10.0.dist-info/WHEEL
naipyext-0.10.0.dist-info/METADATA
naipyext-0.10.0.dist-info/licenses/LICENSE
naipyext-0.10.0.dist-info/RECORD
